spatia/__init__.py
spatia-0.0.1.dist-info/licenses/LICENSE.txt
spatia-0.0.1.dist-info/METADATA
spatia-0.0.1.dist-info/WHEEL
spatia-0.0.1.dist-info/top_level.txt
spatia-0.0.1.dist-info/RECORD
