Metadata-Version: 2.4
Name: spatia
Version: 0.0.1
Summary: Description
Home-page: https://github.com/Bailey3D/spatia
Author: Bailey3D
Author-email: bailey@bailey3d.com
License: MIT
Keywords: spatia
Classifier: Development Status :: 3 - Alpha
Classifier: License :: OSI Approved :: MIT License
Classifier: Programming Language :: Python :: 3
Classifier: Operating System :: OS Independent
License-File: LICENSE.txt
Requires-Dist: numpy
Requires-Dist: scipy
Dynamic: author
Dynamic: author-email
Dynamic: classifier
Dynamic: description
Dynamic: home-page
Dynamic: keywords
Dynamic: license
Dynamic: license-file
Dynamic: requires-dist
Dynamic: summary
